[
   {
      "Title": "Buy book",
      "Completed": true,
      "CreatedAt": "2024-10-30T01:08:11.0198202+05:30",
      "CompletedAt": "2024-10-30T01:08:11.0198202+05:30"
   },
   {
      "Title": "Clean my room",
      "Completed": true,
      "CreatedAt": "2024-10-30T01:08:11.0198202+05:30",
      "CompletedAt": "2024-10-30T03:03:10.0617125+05:30"
   },
   {
      "Title": "Go for a run",
      "Completed": false,
      "CreatedAt": "2024-10-30T02:45:08.2108585+05:30",
      "CompletedAt": null
   },
   {
      "Title": "Do laundry",
      "Completed": true,
      "CreatedAt": "2024-10-30T03:04:42.3055441+05:30",
      "CompletedAt": "2024-10-30T03:06:29.8897324+05:30"
   }
]